<?xml version="1.0" encoding="UTF-8" standalone="yes"?>
<workers>
  <worker>
    <id>1</id>
    <username>adre</username>
    <first_name/>
    <last_name/>
    <email/>
    <job_tag/>
  </worker>
  <worker>
    <id>3</id>
    <username>5645645</username>
    <first_name/>
    <last_name/>
    <email/>
    <job_tag/>
  </worker>
  <worker>
    <id>4</id>
    <username>jon</username>
    <first_name/>
    <last_name/>
    <email/>
    <job_tag/>
  </worker>
  <worker>
    <id>5</id>
    <username>241241</username>
    <first_name/>
    <last_name/>
    <email/>
    <job_tag/>
  </worker>
  <worker>
    <id>6</id>
    <username>52135</username>
    <first_name/>
    <last_name/>
    <email/>
    <job_tag/>
  </worker>
  <worker>
    <id>7</id>
    <username>1241</username>
    <first_name/>
    <last_name/>
    <email/>
    <job_tag/>
  </worker>
  <worker>
    <id>8</id>
    <username>пцупцуп</username>
    <first_name/>
    <last_name/>
    <email/>
    <job_tag/>
  </worker>
  <worker>
    <id>9</id>
    <username/>
    <first_name/>
    <last_name/>
    <email/>
    <job_tag/>
  </worker>
  <worker>
    <id>10</id>
    <username>АЙЦАЙ</username>
    <first_name/>
    <last_name/>
    <email/>
    <job_tag/>
  </worker>
  <worker>
    <id>11</id>
    <username>ma</username>
    <first_name/>
    <last_name/>
    <email/>
    <job_tag/>
  </worker>
  <worker>
    <id>12</id>
    <username>maп</username>
    <first_name/>
    <last_name/>
    <email/>
    <job_tag/>
  </worker>
  <worker>
    <id>14</id>
    <username>mas</username>
    <first_name/>
    <last_name/>
    <email/>
    <job_tag/>
  </worker>
  <worker>
    <id>18</id>
    <username>cat</username>
    <first_name>teryt</first_name>
    <last_name>asdads</last_name>
    <email>adasd@asadas</email>
    <job_tag>teacher</job_tag>
  </worker>
  <worker>
    <id>20</id>
    <username>cat3</username>
    <first_name>Andrey</first_name>
    <last_name>Postelnik</last_name>
    <email>my@mail</email>
    <job_tag>astronaut</job_tag>
  </worker>
</workers>